examples/demo_script.py
retrievify/__init__.py
retrievify/chunker.py
retrievify/cli.py
retrievify/embed.py
retrievify/generate.py
retrievify/index.py
retrievify/rag.py
retrievify/retrieve.py
retrievify/store.py
retrievify/utils.py
retrievify-0.1.4.dist-info/licenses/LICENSE
tests/test_pipeline.py
tests/test_smoke.py
retrievify-0.1.4.dist-info/METADATA
retrievify-0.1.4.dist-info/WHEEL
retrievify-0.1.4.dist-info/entry_points.txt
retrievify-0.1.4.dist-info/top_level.txt
retrievify-0.1.4.dist-info/RECORD
